mechkit/__init__.py
mechkit/fabric_tensors.py
mechkit/material.py
mechkit/notation.py
mechkit/operators.py
mechkit/tensors.py
mechkit/utils.py
mechkit/visualization.py
mechkit-0.4.1.dist-info/LICENSE
mechkit-0.4.1.dist-info/METADATA
mechkit-0.4.1.dist-info/WHEEL
mechkit-0.4.1.dist-info/top_level.txt
mechkit-0.4.1.dist-info/RECORD
