Metadata-Version: 2.1
Name: mechkit
Version: 0.4.1
Summary: Continuum mechanics toolkit
Home-page: https://github.com/JulianKarlBauer/mechkit
Author: Julian Karl Bauer
Author-email: JulianKarlBauer@gmx.de
Classifier: Programming Language :: Python
Classifier: License :: OSI Approved :: MIT License
Classifier: Operating System :: OS Independent
License-File: LICENSE
Requires-Dist: setuptools
Requires-Dist: numpy
Requires-Dist: decorator (==4.3.0) ; python_version <= "2.7"
Requires-Dist: networkx (==2.2) ; python_version <= "2.7"
Requires-Dist: networkx ; python_version > "2.7"
Requires-Dist: sympy ; python_version > "3.6"
